setup.py
DialAgent/__init__.py
DialAgent/dial.py
DialAgent/proxy.py
DialAgent.egg-info/PKG-INFO
DialAgent.egg-info/SOURCES.txt
DialAgent.egg-info/dependency_links.txt
DialAgent.egg-info/requires.txt
DialAgent.egg-info/top_level.txt